trame/__init__.py
trame/modules/__init__.py
trame/modules/tauri.py
trame/widgets/__init__.py
trame/widgets/tauri.py
trame_tauri/__init__.py
trame_tauri/module/__init__.py
trame_tauri/module/serve/trame-tauri.umd.js
trame_tauri/widgets/__init__.py
trame_tauri/widgets/tauri.py
trame_tauri-1.0.2.dist-info/METADATA
trame_tauri-1.0.2.dist-info/WHEEL
trame_tauri-1.0.2.dist-info/licenses/LICENSE
trame_tauri-1.0.2.dist-info/RECORD
