Metadata-Version: 2.4
Name: trame-tauri
Version: 1.0.2
Summary: Helper widget to provide simpler integration with Tauri
Author: Kitware Inc.
License: Apache Software License
License-File: LICENSE
Keywords: Application,Framework,Interactive,Python,Web
Classifier: Development Status :: 5 - Production/Stable
Classifier: Environment :: Web Environment
Classifier: License :: OSI Approved :: Apache Software License
Classifier: Natural Language :: English
Classifier: Operating System :: OS Independent
Classifier: Programming Language :: Python :: 3 :: Only
Classifier: Topic :: Software Development :: Libraries :: Application Frameworks
Classifier: Topic :: Software Development :: Libraries :: Python Modules
Requires-Python: >=3.9
Requires-Dist: trame-client
Provides-Extra: dev
Requires-Dist: pre-commit; extra == 'dev'
Requires-Dist: pytest; extra == 'dev'
Requires-Dist: ruff; extra == 'dev'
